MANIFEST.in
README.rst
setup.py
plugin/__init__.py
plugin/cli/__init__.py
plugin/cli/dump_gapic_v1.py
plugin/cli/gapic_plugin.py
plugin/pb2/__init__.py
plugin/pb2/resource_pb2.py
plugin/templates/__init__.py
plugin/templates/deprecated_parent_resource_name.mustache
plugin/templates/multi_pattern_resource_name.mustache
plugin/templates/resource_name.mustache
plugin/templates/resource_name.py
plugin/templates/resource_name_factory.mustache
plugin/templates/resource_name_fixed.mustache
plugin/templates/untyped_resource_name.mustache
plugin/utils/__init__.py
plugin/utils/casing_utils.py
plugin/utils/gapic_utils.py
plugin/utils/path_template.py
plugin/utils/proto_utils.py
plugin/utils/symbol_table.py
protoc_java_resource_names_plugin.egg-info/PKG-INFO
protoc_java_resource_names_plugin.egg-info/SOURCES.txt
protoc_java_resource_names_plugin.egg-info/dependency_links.txt
protoc_java_resource_names_plugin.egg-info/entry_points.txt
protoc_java_resource_names_plugin.egg-info/requires.txt
protoc_java_resource_names_plugin.egg-info/top_level.txt
test/test_casing_utils.py
test/test_config_parsing.py
test/test_gapic_utils.py
test/test_plugin_baseline.py
test/test_symbol_table.py