Metadata-Version: 1.1
Name: protoc-java-resource-names-plugin
Version: 0.0.20
Summary: Protobuf compiler plugin for Java resource names
Home-page: https://github.com/googleapis/protoc-java-resource-names-plugin
Author: Google API Authors
Author-email: googleapis-packages@google.com
License: BSD-3-Clause
Platform: UNKNOWN
Classifier: Development Status :: 3 - Alpha
Classifier: Intended Audience :: Developers
Classifier: License :: OSI Approved :: BSD License
Classifier: Programming Language :: Python
Classifier: Programming Language :: Python :: 2.7
Classifier: Programming Language :: Python :: 3.4
Classifier: Programming Language :: Python :: 3.5
Classifier: Programming Language :: Python :: 3.6
